LICENSE
MANIFEST.in
README.rst
setup.cfg
setup.py
versioneer.py
tests/__init__.py
tests/test_general.py
tpRigToolkit/__init__.py
tpRigToolkit/__logging__.ini
tpRigToolkit/__version__.py
tpRigToolkit/_version.py
tpRigToolkit/loader.py
tpRigToolkit/core/__init__.py
tpRigToolkit/core/consts.py
tpRigToolkit/core/control.py
tpRigToolkit/core/tool.py
tpRigToolkit/core/utils.py
tpRigToolkit/data/__init__.py
tpRigToolkit/data/controlcv.py
tpRigToolkit/data/spaceswitch.py
tpRigToolkit/data/curves/__init__.py
tpRigToolkit/dccs/__init__.py
tpRigToolkit/libs/__init__.py
tpRigToolkit/managers/__init__.py
tpRigToolkit/managers/data.py
tpRigToolkit/managers/names.py
tpRigToolkit/managers/packages.py
tpRigToolkit/managers/scripts.py
tpRigToolkit/packages/__init__.py
tpRigToolkit/plugins/__init__.py
tpRigToolkit/plugins/renamer.py
tpRigToolkit/plugins/scripteditor.py
tpRigToolkit/tools/__init__.py
tpRigToolkit/toolsets/__init__.py
tpRigToolkit/toolsets/animation.toolset
tpRigToolkit/toolsets/general.toolset
tpRigToolkit/toolsets/nomenclature.toolset
tpRigToolkit/toolsets/rigging.toolset
tpRigToolkit/widgets/__init__.py
tpRigToolkit/widgets/dialog.py
tpRigToolkit/widgets/project.py
tpRigToolkit/widgets/window.py
tpRigToolkit/widgets/options/__init__.py
tpRigToolkit/widgets/options/bone.py
tpRigToolkit/widgets/options/bonecontrollink.py
tpRigToolkit/widgets/options/control.py
tpRigToolkit/widgets/options/factory.py
tpRigToolkit/widgets/options/rigoption.py
tpRigToolkit/widgets/options/rigoptionlist.py
tpRigToolkit/widgets/options/rigoptionsviewer.py
tpRigToolkit_core.egg-info/PKG-INFO
tpRigToolkit_core.egg-info/SOURCES.txt
tpRigToolkit_core.egg-info/dependency_links.txt
tpRigToolkit_core.egg-info/not-zip-safe
tpRigToolkit_core.egg-info/requires.txt
tpRigToolkit_core.egg-info/top_level.txt