Metadata-Version: 2.1
Name: tpRigToolkit-core
Version: 0.0.5
Summary: Framework that contains multiple tools to make rigs
Home-page: https://github.com/tpRigToolkit/tpRigToolkit-core
Author: Tomas Poveda
Author-email: tpovedatd@gmail.com
License: MIT
Platform: UNKNOWN
Provides-Extra: dev
Provides-Extra: test
